blindbox/__init__.py
blindbox/command/aws-nitro/aws-nitro.yml
blindbox/command/aws-nitro/test-tf/.terraform.lock.hcl
blindbox/command/aws-nitro/test-tf/main.tf
blindbox/command/aws-nitro/test_dir/Dockerfile
blindbox/command/aws-nitro/test_dir/app.py
blindbox/command/azure-sev/Dockerfile
blindbox/command/azure-sev/attestation/attest/attest.go
blindbox/command/azure-sev/attestation/attest/certcache.go
blindbox/command/azure-sev/attestation/attest/maa.go
blindbox/command/azure-sev/attestation/attest/snp.go
blindbox/command/azure-sev/attestation/common/http.go
blindbox/command/azure-sev/attestation/common/info.go
blindbox/command/azure-sev/attestation/go.mod
blindbox/command/azure-sev/attestation/go.sum
blindbox/command/azure-sev/attestation/main.go
blindbox/command/azure-sev/attestation/tools/get-snp-report/Makefile
blindbox/command/azure-sev/attestation/tools/get-snp-report/fetch5.h
blindbox/command/azure-sev/attestation/tools/get-snp-report/fetch6.h
blindbox/command/azure-sev/attestation/tools/get-snp-report/get-snp-report.c
blindbox/command/azure-sev/attestation/tools/get-snp-report/get-snp-report5.c
blindbox/command/azure-sev/attestation/tools/get-snp-report/get-snp-report6.c
blindbox/command/azure-sev/attestation/tools/get-snp-report/helpers.c
blindbox/command/azure-sev/attestation/tools/get-snp-report/helpers.h
blindbox/command/azure-sev/attestation/tools/get-snp-report/snp-attestation.h
blindbox/command/azure-sev/attestation/tools/get-snp-report/snp-ioctl5.h
blindbox/command/azure-sev/attestation/tools/get-snp-report/snp-ioctl6.h
blindbox/command/azure-sev/attestation/tools/get-snp-report/snp-psp.h
blindbox/command/azure-sev/sev-init.sh
blindbox/command/azure-sev/sev-start.sh
blindbox/command/azure-sev/template.gitignore
blindbox/command/azure-sev/template.tf
blindbox/command/azure-sev/template.yml
blindbox/command/builder.py
blindbox/command/tests.py
blindbox/requests/__init__.py
blindbox/requests/errors.py
blindbox/requests/requests.py
blindbox-0.2.1.dist-info/METADATA
blindbox-0.2.1.dist-info/WHEEL
blindbox-0.2.1.dist-info/entry_points.txt
blindbox-0.2.1.dist-info/RECORD
