Metadata-Version: 2.1
Name: blindbox
Version: 0.2.1
Summary: BlindBox is a tool to isolate and deploy applications inside Trusted Execution Environments for privacy-by-design apps
Author: Mithril Security
Author-email: contact@mithrilsecurity.io
Requires-Python: >=3.8,<4.0
Classifier: Programming Language :: Python :: 3
Classifier: Programming Language :: Python :: 3.8
Classifier: Programming Language :: Python :: 3.9
Classifier: Programming Language :: Python :: 3.10
Classifier: Programming Language :: Python :: 3.11
Provides-Extra: cli
Requires-Dist: cbor2 (>=5.4.6,<6.0.0)
Requires-Dist: cryptography (>=39.0.2,<40.0.0)
Requires-Dist: inquirer (>=3.1,<4.0) ; extra == "cli"
Requires-Dist: pyOpenSSL (>=23.1.1,<24.0.0)
Requires-Dist: pycose (>=1.0.1,<2.0.0)
Requires-Dist: pydantic (>=1.10.7,<2.0.0) ; extra == "cli"
Requires-Dist: pyjwt (>=2.7.0,<3.0.0)
Requires-Dist: pyyaml (>=6.0,<7.0) ; extra == "cli"
Requires-Dist: requests (>=2.28.2,<3.0.0)
Requires-Dist: rich (>=13.3.5,<14.0.0) ; extra == "cli"
